ontotype/__init__.py
ontotype/py.typed
ontotype-0.1.0.dist-info/METADATA
ontotype-0.1.0.dist-info/WHEEL
ontotype-0.1.0.dist-info/licenses/LICENSE
ontotype-0.1.0.dist-info/RECORD
