Metadata-Version: 2.4
Name: ontotype
Version: 0.1.0
Summary: Extended python types.
Author-email: Hart Traveller <ruling_fiction.0b@icloud.com>
License-File: LICENSE
Requires-Python: >=3.11
